LICENSE
MANIFEST.in
README.rst
setup.py
django_ecstatic.egg-info/PKG-INFO
django_ecstatic.egg-info/SOURCES.txt
django_ecstatic.egg-info/dependency_links.txt
django_ecstatic.egg-info/not-zip-safe
django_ecstatic.egg-info/requires.txt
django_ecstatic.egg-info/top_level.txt
ecstatic/__init__.py
ecstatic/conf.py
ecstatic/manifests.py
ecstatic/models.py
ecstatic/pkgmeta.py
ecstatic/storage.py
ecstatic/utils.py
ecstatic/views.py
ecstatic/management/__init__.py
ecstatic/management/utils.py
ecstatic/management/commands/__init__.py
ecstatic/management/commands/createstaticmanifest.py
ecstatic/management/commands/eccollect.py
ecstatic/management/commands/hashmedianames.py
tests/__init__.py
tests/settings.py