Metadata-Version: 1.0
Name: django-ecstatic
Version: 0.1
Summary: An expansion pack for django.contrib.staticfiles!
Home-page: http://github.com/hzdg/django-ecstatic
Author: Matthew Tretter
Author-email: m@tthewwithanm.com
License: UNKNOWN
Download-URL: http://github.com/hzdg/django-ecstatic/tarball/master
Platform: UNKNOWN
Classifier: Development Status :: 5 - Production/Stable
Classifier: Environment :: Web Environment
Classifier: Framework :: Django
Classifier: Intended Audience :: Developers
Classifier: License :: OSI Approved :: BSD License
Classifier: Operating System :: OS Independent
Classifier: Programming Language :: Python :: 2.5
Classifier: Programming Language :: Python :: 2.6
Classifier: Programming Language :: Python :: 2.7
Classifier: Topic :: Utilities
